quadrant_gen/__init__.py
quadrant_gen/chart.py
quadrant_gen-0.2.0.dist-info/METADATA
quadrant_gen-0.2.0.dist-info/WHEEL
quadrant_gen-0.2.0.dist-info/top_level.txt
quadrant_gen-0.2.0.dist-info/RECORD
