Metadata-Version: 2.2
Name: quadrant-gen
Version: 0.2.0
Summary: A library for creating quadrant charts with base64 output
Home-page: https://github.com/ceccode/quadrant-gen
Author: Francesco
Author-email: falanga.fra@gmail.com
Project-URL: Bug Reports, https://github.com/ceccode/quadrant-gen/issues
Project-URL: Source, https://github.com/ceccode/quadrant-gen
Keywords: quadrant,chart,visualization,matplotlib,csv
Classifier: Programming Language :: Python :: 3
Classifier: Programming Language :: Python :: 3.7
Classifier: Programming Language :: Python :: 3.8
Classifier: Programming Language :: Python :: 3.9
Classifier: Programming Language :: Python :: 3.10
Classifier: License :: OSI Approved :: MIT License
Classifier: Operating System :: OS Independent
Classifier: Intended Audience :: Developers
Classifier: Intended Audience :: Science/Research
Classifier: Topic :: Scientific/Engineering :: Visualization
Requires-Python: >=3.7
Requires-Dist: matplotlib>=3.5.0
Requires-Dist: numpy>=1.20.0
Dynamic: author
Dynamic: author-email
Dynamic: classifier
Dynamic: description
Dynamic: description-content-type
Dynamic: home-page
Dynamic: keywords
Dynamic: project-url
Dynamic: requires-dist
Dynamic: requires-python
Dynamic: summary
